MANIFEST.in
README.md
setup.py
asyncmc/__init__.py
asyncmc/client.py
asyncmc/constants.py
asyncmc/exceptions.py
asyncmc/host.py
asyncmc/pool.py
asyncmc.egg-info/PKG-INFO
asyncmc.egg-info/SOURCES.txt
asyncmc.egg-info/dependency_links.txt
asyncmc.egg-info/requires.txt
asyncmc.egg-info/top_level.txt
tests/__init__.py
tests/_testutil.py
tests/test_client.py
tests/test_host.py
tests/test_pool.py