Metadata-Version: 1.1
Name: asyncmc
Version: 0.6.7
Summary: Minimal pure python tornado memcached client
Home-page: https://github.com/ErDmKo/asyncmc/
Author: Eroshenko Dmitriy
Author-email: erdmko@gmail.com
License: MIT
Platform: UNKNOWN
Classifier: License :: OSI Approved :: MIT License
Classifier: Development Status :: 3 - Alpha
Classifier: Intended Audience :: Developers
Classifier: Programming Language :: Python
Classifier: Programming Language :: Python :: 2.7
Classifier: Programming Language :: Python :: 3
Classifier: Operating System :: POSIX
Classifier: Operating System :: MacOS :: MacOS X
Classifier: Operating System :: Microsoft :: Windows
Classifier: Environment :: Web Environment
